sagemaker_jupyterlab_extension_common/__init__.py
sagemaker_jupyterlab_extension_common/_version.py
sagemaker_jupyterlab_extension_common/clients.py
sagemaker_jupyterlab_extension_common/constants.py
sagemaker_jupyterlab_extension_common/default_sagemaker_client.py
sagemaker_jupyterlab_extension_common/dual_stack_utils.py
sagemaker_jupyterlab_extension_common/exceptions.py
sagemaker_jupyterlab_extension_common/executor.py
sagemaker_jupyterlab_extension_common/file_utils.py
sagemaker_jupyterlab_extension_common/handlers.py
sagemaker_jupyterlab_extension_common/identity.py
sagemaker_jupyterlab_extension_common/py.typed
sagemaker_jupyterlab_extension_common/botocore_model/sagemaker/2017-07-24/service-2.json
sagemaker_jupyterlab_extension_common/jumpstart/__init__.py
sagemaker_jupyterlab_extension_common/jumpstart/constants.py
sagemaker_jupyterlab_extension_common/jumpstart/handlers.py
sagemaker_jupyterlab_extension_common/jumpstart/logging_utils.py
sagemaker_jupyterlab_extension_common/jumpstart/notebook_transformation.py
sagemaker_jupyterlab_extension_common/jumpstart/notebook_types.py
sagemaker_jupyterlab_extension_common/jumpstart/notebook_utils.py
sagemaker_jupyterlab_extension_common/jumpstart/nova_prime_validator.py
sagemaker_jupyterlab_extension_common/jumpstart/request.py
sagemaker_jupyterlab_extension_common/jumpstart/stage_utils.py
sagemaker_jupyterlab_extension_common/labextension/package.json
sagemaker_jupyterlab_extension_common/labextension/static/117.e01e1fff3ce2e26893fe.js
sagemaker_jupyterlab_extension_common/labextension/static/38.7a81b26e54121afe0f4e.js
sagemaker_jupyterlab_extension_common/labextension/static/432.d8ee7cc512a435d5db85.js
sagemaker_jupyterlab_extension_common/labextension/static/512.0d11e8e2f811e7eced9c.js
sagemaker_jupyterlab_extension_common/labextension/static/64.e9eca6474b8b8bfaaf99.js
sagemaker_jupyterlab_extension_common/labextension/static/687.d1a4669887f7c4f5716c.js
sagemaker_jupyterlab_extension_common-0.2.16.dist-info/licenses/LICENSE
sagemaker_jupyterlab_extension_common-0.2.16.dist-info/METADATA
sagemaker_jupyterlab_extension_common-0.2.16.dist-info/WHEEL
sagemaker_jupyterlab_extension_common-0.2.16.dist-info/top_level.txt
sagemaker_jupyterlab_extension_common-0.2.16.dist-info/RECORD
