Metadata-Version: 2.4
Name: sagemaker-jupyterlab-extension-common
Version: 0.2.16
Summary: SageMaker JupyterLab workspace common module
Home-page: https://aws.amazon.com/sagemaker/
Author: Amazon
License: Amazon Software License
Keywords: Jupyter,JupyterLab,JupyterLab4
Platform: Linux
Platform: Mac OS X
Platform: Windows
Classifier: Programming Language :: Python
Classifier: Programming Language :: Python :: 3
Classifier: Programming Language :: Python :: 3.9
Classifier: Framework :: Jupyter
Requires-Python: >=3.9
License-File: LICENSE
Requires-Dist: boto3
Requires-Dist: jupyterlab>=4
Requires-Dist: jupyter-events>=0.6.0
Requires-Dist: aiobotocore>=2.7.0
Requires-Dist: aws_embedded_metrics
Requires-Dist: y-py<0.7.0,>=0.6.0
Requires-Dist: ypy-websocket>=0.12.0
Requires-Dist: nbformat>=5.9.2
Requires-Dist: pydantic<3,>=1.10.17
Requires-Dist: pyjwt<3.0.0,>=2.10.0
Provides-Extra: dev
Requires-Dist: pytest>=6; extra == "dev"
Requires-Dist: pytest-cov; extra == "dev"
Requires-Dist: black; extra == "dev"
Requires-Dist: pytest-asyncio; extra == "dev"
Requires-Dist: pytest_jupyter; extra == "dev"
Dynamic: author
Dynamic: classifier
Dynamic: description
Dynamic: description-content-type
Dynamic: home-page
Dynamic: keywords
Dynamic: license
Dynamic: license-file
Dynamic: platform
Dynamic: provides-extra
Dynamic: requires-dist
Dynamic: requires-python
Dynamic: summary
